octocheese/__init__.py
octocheese/__main__.py
octocheese/action.py
octocheese/colours.py
octocheese/core.py
octocheese/py.typed
octocheese-0.7.0.dist-info/LICENSE
octocheese-0.7.0.dist-info/METADATA
octocheese-0.7.0.dist-info/WHEEL
octocheese-0.7.0.dist-info/entry_points.txt
octocheese-0.7.0.dist-info/RECORD
