Metadata-Version: 2.1
Name: octocheese
Version: 0.7.0
Summary: 🐙 🧀 – Copy PyPI Packages to GitHub Releases
Author-email: Dominic Davis-Foster <dominic@davis-foster.co.uk>
License: LGPL-3.0-or-later
Keywords: github,github-action,pypi
Home-page: https://github.com/domdfcoding/octocheese
Project-URL: Issue Tracker, https://github.com/domdfcoding/octocheese/issues
Project-URL: Source Code, https://github.com/domdfcoding/octocheese
Project-URL: Documentation, https://octocheese.readthedocs.io/en/latest
Platform: Windows
Platform: macOS
Platform: Linux
Classifier: Development Status :: 4 - Beta
Classifier: Intended Audience :: Developers
Classifier: License :: OSI Approved :: GNU Lesser General Public License v3 or later (LGPLv3+)
Classifier: Operating System :: OS Independent
Classifier: Programming Language :: Python
Classifier: Programming Language :: Python :: 3 :: Only
Classifier: Programming Language :: Python :: 3.6
Classifier: Programming Language :: Python :: 3.7
Classifier: Programming Language :: Python :: 3.8
Classifier: Programming Language :: Python :: 3.9
Classifier: Programming Language :: Python :: 3.10
Classifier: Programming Language :: Python :: 3.11
Classifier: Programming Language :: Python :: 3.12
Classifier: Programming Language :: Python :: Implementation :: CPython
Classifier: Topic :: Utilities
Classifier: Typing :: Typed
Requires-Python: >=3.6
Requires-Dist: apeye-core>=1.0.0
Requires-Dist: click>=7.1.2
Requires-Dist: consolekit>=0.8.2
Requires-Dist: domdf-python-tools>=1.5.0
Requires-Dist: dulwich!=0.20.7,!=0.20.8,>=0.20.5
Requires-Dist: github3-py>=1.3.0
Requires-Dist: github3-utils>=0.3.0
Requires-Dist: packaging>=21.3
Requires-Dist: pypi-json>=0.2.1
Requires-Dist: shippinglabel>=0.6.1
Requires-Dist: typing-extensions>=3.7.4.3
